djangocms_grid/__init__.py
djangocms_grid/cms_plugins.py
djangocms_grid/forms.py
djangocms_grid/models.py
djangocms_grid/locale/af/LC_MESSAGES/django.mo
djangocms_grid/locale/af/LC_MESSAGES/django.po
djangocms_grid/locale/ar/LC_MESSAGES/django.mo
djangocms_grid/locale/ar/LC_MESSAGES/django.po
djangocms_grid/locale/be/LC_MESSAGES/django.mo
djangocms_grid/locale/be/LC_MESSAGES/django.po
djangocms_grid/locale/bg/LC_MESSAGES/django.mo
djangocms_grid/locale/bg/LC_MESSAGES/django.po
djangocms_grid/locale/bn/LC_MESSAGES/django.mo
djangocms_grid/locale/bn/LC_MESSAGES/django.po
djangocms_grid/locale/ca/LC_MESSAGES/django.mo
djangocms_grid/locale/ca/LC_MESSAGES/django.po
djangocms_grid/locale/cmn/LC_MESSAGES/django.mo
djangocms_grid/locale/cmn/LC_MESSAGES/django.po
djangocms_grid/locale/cs/LC_MESSAGES/django.mo
djangocms_grid/locale/cs/LC_MESSAGES/django.po
djangocms_grid/locale/cy/LC_MESSAGES/django.mo
djangocms_grid/locale/cy/LC_MESSAGES/django.po
djangocms_grid/locale/da/LC_MESSAGES/django.mo
djangocms_grid/locale/da/LC_MESSAGES/django.po
djangocms_grid/locale/de/LC_MESSAGES/django.mo
djangocms_grid/locale/de/LC_MESSAGES/django.po
djangocms_grid/locale/el/LC_MESSAGES/django.mo
djangocms_grid/locale/el/LC_MESSAGES/django.po
djangocms_grid/locale/en/LC_MESSAGES/django.mo
djangocms_grid/locale/en/LC_MESSAGES/django.po
djangocms_grid/locale/es/LC_MESSAGES/django.mo
djangocms_grid/locale/es/LC_MESSAGES/django.po
djangocms_grid/locale/es_AR/LC_MESSAGES/django.mo
djangocms_grid/locale/es_AR/LC_MESSAGES/django.po
djangocms_grid/locale/es_BO/LC_MESSAGES/django.mo
djangocms_grid/locale/es_BO/LC_MESSAGES/django.po
djangocms_grid/locale/es_DO/LC_MESSAGES/django.mo
djangocms_grid/locale/es_DO/LC_MESSAGES/django.po
djangocms_grid/locale/et/LC_MESSAGES/django.mo
djangocms_grid/locale/et/LC_MESSAGES/django.po
djangocms_grid/locale/eu/LC_MESSAGES/django.mo
djangocms_grid/locale/eu/LC_MESSAGES/django.po
djangocms_grid-1.3.0.dist-info/DESCRIPTION.rst
djangocms_grid-1.3.0.dist-info/METADATA
djangocms_grid-1.3.0.dist-info/metadata.json
djangocms_grid-1.3.0.dist-info/RECORD
djangocms_grid-1.3.0.dist-info/top_level.txt
djangocms_grid-1.3.0.dist-info/WHEEL
